<?xml version="1.0" encoding="UTF-8" standalone="yes" ?>
<!DOCTYPE ZapfTable [
<!ELEMENT ZapfTable ((glyphInfo*), (namedGroupGroup*), (namedGlyphGroup*), (featureInfo*))>
<!ELEMENT glyphInfo (fontGlyph, (unicodeList?), (universalName?), (appleName?), (adobeName?), (AFIIName?), (unicodeLikeName?), (CIDJapanese?), (CIDTraditionalChinese?), (CIDSimplifiedChinese?), (CIDKorean?), (versionHistoryNote?), (designerShortName?), (designerLongName?), (designerUsageNote?), (designerHistoricalNote?))>
<!ELEMENT namedGlyphGroup ((fontName?), (fontGlyph+))>
<!ELEMENT namedGroupGroup ((fontName?), (namedGlyphGroup+))>
<!ELEMENT featureInfo ((fontGlyph+), (aatFeature*), (otFeatureTag*))>
<!ELEMENT fontGlyph EMPTY>
<!ELEMENT unicodeList (unicode+)>
<!ELEMENT unicode EMPTY>
<!ELEMENT universalName EMPTY>
<!ELEMENT appleName EMPTY>
<!ELEMENT adobeName EMPTY>
<!ELEMENT AFIIName EMPTY>
<!ELEMENT unicodeLikeName EMPTY>
<!ELEMENT CIDJapanese EMPTY>
<!ELEMENT CIDTraditionalChinese EMPTY>
<!ELEMENT CIDSimplifiedChinese EMPTY>
<!ELEMENT CIDKorean EMPTY>
<!ELEMENT versionHistoryNote (fontName)>
<!ELEMENT designerShortName (fontName)>
<!ELEMENT designerLongName (fontName)>
<!ELEMENT designerUsageNote (fontName)>
<!ELEMENT designerHistoricalNote (fontName)>
<!ELEMENT fontName EMPTY>
<!ELEMENT aatFeature EMPTY>
<!ELEMENT otFeatureTag EMPTY>
<!ATTLIST ZapfTable  version CDATA  #REQUIRED >
<!ATTLIST unicode  value    CDATA  #REQUIRED
	charName CDATA  #IMPLIED >
<!ATTLIST featureInfo  context CDATA  #REQUIRED >
<!ATTLIST universalName  value CDATA  #REQUIRED >
<!ATTLIST appleName  value CDATA  #REQUIRED >
<!ATTLIST adobeName  value CDATA  #REQUIRED >
<!ATTLIST AFIIName  value CDATA  #REQUIRED >
<!ATTLIST unicodeLikeName  value CDATA  #REQUIRED >
<!ATTLIST CIDJapanese  value CDATA  #REQUIRED >
<!ATTLIST CIDTraditionalChinese  value CDATA  #REQUIRED >
<!ATTLIST CIDSimplifiedChinese  value CDATA  #REQUIRED >
<!ATTLIST CIDKorean  value CDATA  #REQUIRED >
<!ATTLIST aatFeature  type CDATA  #REQUIRED
			setting CDATA #REQUIRED >
<!ATTLIST otFeatureTag  value CDATA  #REQUIRED >
<!ATTLIST fontGlyph  glyphRefID CDATA  #REQUIRED
	glyphName  CDATA  #IMPLIED >
<!ATTLIST fontName  nameRefID  CDATA  #REQUIRED
	nameString CDATA  #IMPLIED >
<!ATTLIST namedGroupGroup isAltForms CDATA #REQUIRED>
<!ATTLIST namedGlyphGroup isAltForms CDATA #REQUIRED>
]>

<!--

	Data generated 	Thu Jun  5 13:44:29 2014

	Generated by ftxanalyzer, version 213
	55
-->

<ZapfTable version="1.0">
	<glyphInfo>
		<fontGlyph glyphRefID="0" glyphName=".notdef" />
		<unicodeList>
			<unicode value="U+F0000" charName="<Private Use Character U+00000>" />
		</unicodeList>
	</glyphInfo>
	<glyphInfo>
		<fontGlyph glyphRefID="1" glyphName="NULL" />
		<unicodeList>
			<unicode value="U+0000" charName="&lt;control&gt;" />
		</unicodeList>
	</glyphInfo>
	<glyphInfo>
		<fontGlyph glyphRefID="2" glyphName="space" />
		<unicodeList>
			<unicode value="U+0020" charName="SPACE" />
		</unicodeList>
	</glyphInfo>
	<glyphInfo>
		<fontGlyph glyphRefID="3" glyphName="uni000D" />
		<unicodeList>
			<unicode value="U+000D" charName="&lt;control&gt;" />
		</unicodeList>
	</glyphInfo>
	<glyphInfo>
		<fontGlyph glyphRefID="4" glyphName="triangle.up" />
		<unicodeList>
			<unicode value="U+E000" charName="&lt;Private Use Character U+E000&gt;" />
		</unicodeList>
	</glyphInfo>
	<glyphInfo>
		<fontGlyph glyphRefID="5" glyphName="triangle.right" />
		<unicodeList>
			<unicode value="U+E001" charName="&lt;Private Use Character U+E001&gt;" />
		</unicodeList>
	</glyphInfo>
	<glyphInfo>
		<fontGlyph glyphRefID="6" glyphName="triangle.down" />
		<unicodeList>
			<unicode value="U+E002" charName="&lt;Private Use Character U+E002&gt;" />
		</unicodeList>
	</glyphInfo>
	<glyphInfo>
		<fontGlyph glyphRefID="7" glyphName="triangle.left" />
		<unicodeList>
			<unicode value="U+E003" charName="&lt;Private Use Character U+E003&gt;" />
		</unicodeList>
	</glyphInfo>
	<glyphInfo>
		<fontGlyph glyphRefID="8" glyphName="chevron.up" />
		<unicodeList>
			<unicode value="U+E00C" charName="&lt;Private Use Character U+E00C&gt;" />
		</unicodeList>
	</glyphInfo>
	<glyphInfo>
		<fontGlyph glyphRefID="9" glyphName="chevron.down" />
		<unicodeList>
			<unicode value="U+E00D" charName="&lt;Private Use Character U+E00D&gt;" />
		</unicodeList>
	</glyphInfo>
	<glyphInfo>
		<fontGlyph glyphRefID="10" glyphName="chevron.left" />
		<unicodeList>
			<unicode value="U+E00E" charName="&lt;Private Use Character U+E00E&gt;" />
		</unicodeList>
	</glyphInfo>
	<glyphInfo>
		<fontGlyph glyphRefID="11" glyphName="chevron.right" />
		<unicodeList>
			<unicode value="U+E00F" charName="&lt;Private Use Character U+E00F&gt;" />
		</unicodeList>
	</glyphInfo>
	<glyphInfo>
		<fontGlyph glyphRefID="12" glyphName="arrow.up" />
		<unicodeList>
			<unicode value="U+E018" charName="&lt;Private Use Character U+E018&gt;" />
		</unicodeList>
	</glyphInfo>
	<glyphInfo>
		<fontGlyph glyphRefID="13" glyphName="arrow.right" />
		<unicodeList>
			<unicode value="U+E019" charName="&lt;Private Use Character U+E019&gt;" />
		</unicodeList>
	</glyphInfo>
	<glyphInfo>
		<fontGlyph glyphRefID="14" glyphName="arrow.down" />
		<unicodeList>
			<unicode value="U+E01A" charName="&lt;Private Use Character U+E01A&gt;" />
		</unicodeList>
	</glyphInfo>
	<glyphInfo>
		<fontGlyph glyphRefID="15" glyphName="arrow.left" />
		<unicodeList>
			<unicode value="U+E01B" charName="&lt;Private Use Character U+E01B&gt;" />
		</unicodeList>
	</glyphInfo>
	<glyphInfo>
		<fontGlyph glyphRefID="16" glyphName="circle.triangle.up.outline" />
		<unicodeList>
			<unicode value="U+E004" charName="&lt;Private Use Character U+E004&gt;" />
		</unicodeList>
	</glyphInfo>
	<glyphInfo>
		<fontGlyph glyphRefID="17" glyphName="circle.triangle.down.outline" />
		<unicodeList>
			<unicode value="U+E005" charName="&lt;Private Use Character U+E005&gt;" />
		</unicodeList>
	</glyphInfo>
	<glyphInfo>
		<fontGlyph glyphRefID="18" glyphName="circle.triangle.left.outline" />
		<unicodeList>
			<unicode value="U+E006" charName="&lt;Private Use Character U+E006&gt;" />
		</unicodeList>
	</glyphInfo>
	<glyphInfo>
		<fontGlyph glyphRefID="19" glyphName="circle.triangle.right.outline" />
		<unicodeList>
			<unicode value="U+E007" charName="&lt;Private Use Character U+E007&gt;" />
		</unicodeList>
	</glyphInfo>
	<glyphInfo>
		<fontGlyph glyphRefID="20" glyphName="circle.triangle.up" />
		<unicodeList>
			<unicode value="U+E008" charName="&lt;Private Use Character U+E008&gt;" />
		</unicodeList>
	</glyphInfo>
	<glyphInfo>
		<fontGlyph glyphRefID="21" glyphName="circle.triangle.down" />
		<unicodeList>
			<unicode value="U+E009" charName="&lt;Private Use Character U+E009&gt;" />
		</unicodeList>
	</glyphInfo>
	<glyphInfo>
		<fontGlyph glyphRefID="22" glyphName="circle.triangle.left" />
		<unicodeList>
			<unicode value="U+E00A" charName="&lt;Private Use Character U+E00A&gt;" />
		</unicodeList>
	</glyphInfo>
	<glyphInfo>
		<fontGlyph glyphRefID="23" glyphName="circle.triangle.right" />
		<unicodeList>
			<unicode value="U+E00B" charName="&lt;Private Use Character U+E00B&gt;" />
		</unicodeList>
	</glyphInfo>
	<glyphInfo>
		<fontGlyph glyphRefID="24" glyphName="square" />
		<unicodeList>
			<unicode value="U+E01C" charName="&lt;Private Use Character U+E01C&gt;" />
		</unicodeList>
	</glyphInfo>
	<glyphInfo>
		<fontGlyph glyphRefID="25" glyphName="square.check" />
		<unicodeList>
			<unicode value="U+E01D" charName="&lt;Private Use Character U+E01D&gt;" />
		</unicodeList>
	</glyphInfo>
	<glyphInfo>
		<fontGlyph glyphRefID="26" glyphName="square.plus" />
		<unicodeList>
			<unicode value="U+E01E" charName="&lt;Private Use Character U+E01E&gt;" />
		</unicodeList>
	</glyphInfo>
	<glyphInfo>
		<fontGlyph glyphRefID="27" glyphName="square.minus" />
		<unicodeList>
			<unicode value="U+E01F" charName="&lt;Private Use Character U+E01F&gt;" />
		</unicodeList>
	</glyphInfo>
	<glyphInfo>
		<fontGlyph glyphRefID="28" glyphName="square.x" />
		<unicodeList>
			<unicode value="U+E020" charName="&lt;Private Use Character U+E020&gt;" />
		</unicodeList>
	</glyphInfo>
	<glyphInfo>
		<fontGlyph glyphRefID="29" glyphName="square.outline" />
		<unicodeList>
			<unicode value="U+E021" charName="&lt;Private Use Character U+E021&gt;" />
		</unicodeList>
	</glyphInfo>
	<glyphInfo>
		<fontGlyph glyphRefID="30" glyphName="square.check.outline" />
		<unicodeList>
			<unicode value="U+E022" charName="&lt;Private Use Character U+E022&gt;" />
		</unicodeList>
	</glyphInfo>
	<glyphInfo>
		<fontGlyph glyphRefID="31" glyphName="square.plus.outline" />
		<unicodeList>
			<unicode value="U+E023" charName="&lt;Private Use Character U+E023&gt;" />
		</unicodeList>
	</glyphInfo>
	<glyphInfo>
		<fontGlyph glyphRefID="32" glyphName="square.minusoutline" />
		<unicodeList>
			<unicode value="U+E024" charName="&lt;Private Use Character U+E024&gt;" />
		</unicodeList>
	</glyphInfo>
	<glyphInfo>
		<fontGlyph glyphRefID="33" glyphName="square.x.outline" />
		<unicodeList>
			<unicode value="U+E025" charName="&lt;Private Use Character U+E025&gt;" />
		</unicodeList>
	</glyphInfo>
	<glyphInfo>
		<fontGlyph glyphRefID="34" glyphName="square.dash" />
		<unicodeList>
			<unicode value="U+E026" charName="&lt;Private Use Character U+E026&gt;" />
		</unicodeList>
	</glyphInfo>
	<glyphInfo>
		<fontGlyph glyphRefID="35" glyphName="square.check.dash" />
		<unicodeList>
			<unicode value="U+E027" charName="&lt;Private Use Character U+E027&gt;" />
		</unicodeList>
	</glyphInfo>
	<glyphInfo>
		<fontGlyph glyphRefID="36" glyphName="square.plus.dash" />
		<unicodeList>
			<unicode value="U+E028" charName="&lt;Private Use Character U+E028&gt;" />
		</unicodeList>
	</glyphInfo>
	<glyphInfo>
		<fontGlyph glyphRefID="37" glyphName="square.minus.dash" />
		<unicodeList>
			<unicode value="U+E029" charName="&lt;Private Use Character U+E029&gt;" />
		</unicodeList>
	</glyphInfo>
	<glyphInfo>
		<fontGlyph glyphRefID="38" glyphName="square.x.dash" />
		<unicodeList>
			<unicode value="U+E02A" charName="&lt;Private Use Character U+E02A&gt;" />
		</unicodeList>
	</glyphInfo>
	<glyphInfo>
		<fontGlyph glyphRefID="39" glyphName="circle.outline" />
		<unicodeList>
			<unicode value="U+E030" charName="&lt;Private Use Character U+E030&gt;" />
		</unicodeList>
	</glyphInfo>
	<glyphInfo>
		<fontGlyph glyphRefID="40" glyphName="circle.check.outline" />
		<unicodeList>
			<unicode value="U+E031" charName="&lt;Private Use Character U+E031&gt;" />
		</unicodeList>
	</glyphInfo>
	<glyphInfo>
		<fontGlyph glyphRefID="41" glyphName="circle.plus.outline" />
		<unicodeList>
			<unicode value="U+E032" charName="&lt;Private Use Character U+E032&gt;" />
		</unicodeList>
	</glyphInfo>
	<glyphInfo>
		<fontGlyph glyphRefID="42" glyphName="circle.minus.outline" />
		<unicodeList>
			<unicode value="U+E033" charName="&lt;Private Use Character U+E033&gt;" />
		</unicodeList>
	</glyphInfo>
	<glyphInfo>
		<fontGlyph glyphRefID="43" glyphName="circle.x.outline" />
		<unicodeList>
			<unicode value="U+E034" charName="&lt;Private Use Character U+E034&gt;" />
		</unicodeList>
	</glyphInfo>
	<glyphInfo>
		<fontGlyph glyphRefID="44" glyphName="circle.chevron.up" />
		<unicodeList>
			<unicode value="U+E014" charName="&lt;Private Use Character U+E014&gt;" />
		</unicodeList>
	</glyphInfo>
	<glyphInfo>
		<fontGlyph glyphRefID="45" glyphName="circle.chevron.down" />
		<unicodeList>
			<unicode value="U+E015" charName="&lt;Private Use Character U+E015&gt;" />
		</unicodeList>
	</glyphInfo>
	<glyphInfo>
		<fontGlyph glyphRefID="46" glyphName="circle.chevron.left" />
		<unicodeList>
			<unicode value="U+E016" charName="&lt;Private Use Character U+E016&gt;" />
		</unicodeList>
	</glyphInfo>
	<glyphInfo>
		<fontGlyph glyphRefID="47" glyphName="circle.chevron.right" />
		<unicodeList>
			<unicode value="U+E017" charName="&lt;Private Use Character U+E017&gt;" />
		</unicodeList>
	</glyphInfo>
	<glyphInfo>
		<fontGlyph glyphRefID="48" glyphName="circle.chevron.up.outline" />
		<unicodeList>
			<unicode value="U+E010" charName="&lt;Private Use Character U+E010&gt;" />
		</unicodeList>
	</glyphInfo>
	<glyphInfo>
		<fontGlyph glyphRefID="49" glyphName="circle.chevron.right.outline" />
		<unicodeList>
			<unicode value="U+E011" charName="&lt;Private Use Character U+E011&gt;" />
		</unicodeList>
	</glyphInfo>
	<glyphInfo>
		<fontGlyph glyphRefID="50" glyphName="circle.chevron.down.outline" />
		<unicodeList>
			<unicode value="U+E012" charName="&lt;Private Use Character U+E012&gt;" />
		</unicodeList>
	</glyphInfo>
	<glyphInfo>
		<fontGlyph glyphRefID="51" glyphName="circle.chevron.left.outline" />
		<unicodeList>
			<unicode value="U+E013" charName="&lt;Private Use Character U+E013&gt;" />
		</unicodeList>
	</glyphInfo>
	<glyphInfo>
		<fontGlyph glyphRefID="52" glyphName="circle" />
		<unicodeList>
			<unicode value="U+E02B" charName="&lt;Private Use Character U+E02B&gt;" />
		</unicodeList>
	</glyphInfo>
	<glyphInfo>
		<fontGlyph glyphRefID="53" glyphName="circle.check" />
		<unicodeList>
			<unicode value="U+E02C" charName="&lt;Private Use Character U+E02C&gt;" />
		</unicodeList>
	</glyphInfo>
	<glyphInfo>
		<fontGlyph glyphRefID="54" glyphName="circle.plus" />
		<unicodeList>
			<unicode value="U+E02D" charName="&lt;Private Use Character U+E02D&gt;" />
		</unicodeList>
	</glyphInfo>
	<glyphInfo>
		<fontGlyph glyphRefID="55" glyphName="circle.minus" />
		<unicodeList>
			<unicode value="U+E02E" charName="&lt;Private Use Character U+E02E&gt;" />
		</unicodeList>
	</glyphInfo>
	<glyphInfo>
		<fontGlyph glyphRefID="56" glyphName="circle.x" />
		<unicodeList>
			<unicode value="U+E02F" charName="&lt;Private Use Character U+E02F&gt;" />
		</unicodeList>
	</glyphInfo>
	<glyphInfo>
		<fontGlyph glyphRefID="57" glyphName="clock" />
		<unicodeList>
			<unicode value="U+E039" charName="&lt;Private Use Character U+E039&gt;" />
		</unicodeList>
	</glyphInfo>
	<glyphInfo>
		<fontGlyph glyphRefID="58" glyphName="clock.invert" />
		<unicodeList>
			<unicode value="U+E03A" charName="&lt;Private Use Character U+E03A&gt;" />
		</unicodeList>
	</glyphInfo>
	<glyphInfo>
		<fontGlyph glyphRefID="59" glyphName="clock.reverse" />
		<unicodeList>
			<unicode value="U+E03B" charName="&lt;Private Use Character U+E03B&gt;" />
		</unicodeList>
	</glyphInfo>
	<glyphInfo>
		<fontGlyph glyphRefID="60" glyphName="uni23F1" />
		<unicodeList>
			<unicode value="U+E03C" charName="&lt;Private Use Character U+E03C&gt;" />
		</unicodeList>
	</glyphInfo>
	<glyphInfo>
		<fontGlyph glyphRefID="61" glyphName="uni23F1.invert" />
		<unicodeList>
			<unicode value="U+E03D" charName="&lt;Private Use Character U+E03D&gt;" />
		</unicodeList>
	</glyphInfo>
	<glyphInfo>
		<fontGlyph glyphRefID="62" glyphName="alarm.clock" />
		<unicodeList>
			<unicode value="U+E03E" charName="&lt;Private Use Character U+E03E&gt;" />
		</unicodeList>
	</glyphInfo>
	<glyphInfo>
		<fontGlyph glyphRefID="63" glyphName="alarm.clock.invert" />
		<unicodeList>
			<unicode value="U+E03F" charName="&lt;Private Use Character U+E03F&gt;" />
		</unicodeList>
	</glyphInfo>
	<glyphInfo>
		<fontGlyph glyphRefID="64" glyphName="comment.outline" />
		<unicodeList>
			<unicode value="U+E035" charName="&lt;Private Use Character U+E035&gt;" />
		</unicodeList>
	</glyphInfo>
	<glyphInfo>
		<fontGlyph glyphRefID="65" glyphName="comment" />
		<unicodeList>
			<unicode value="U+E036" charName="&lt;Private Use Character U+E036&gt;" />
		</unicodeList>
	</glyphInfo>
	<glyphInfo>
		<fontGlyph glyphRefID="66" glyphName="reply" />
		<unicodeList>
			<unicode value="U+E037" charName="&lt;Private Use Character U+E037&gt;" />
		</unicodeList>
	</glyphInfo>
	<glyphInfo>
		<fontGlyph glyphRefID="67" glyphName="reply.outline" />
		<unicodeList>
			<unicode value="U+E038" charName="&lt;Private Use Character U+E038&gt;" />
		</unicodeList>
	</glyphInfo>
	<glyphInfo>
		<fontGlyph glyphRefID="68" glyphName="reorder" />
		<unicodeList>
			<unicode value="U+E044" charName="&lt;Private Use Character U+E044&gt;" />
		</unicodeList>
	</glyphInfo>
	<glyphInfo>
		<fontGlyph glyphRefID="69" glyphName="ul" />
		<unicodeList>
			<unicode value="U+E045" charName="&lt;Private Use Character U+E045&gt;" />
		</unicodeList>
	</glyphInfo>
	<glyphInfo>
		<fontGlyph glyphRefID="70" glyphName="cal" />
		<unicodeList>
			<unicode value="U+E041" charName="&lt;Private Use Character U+E041&gt;" />
		</unicodeList>
	</glyphInfo>
	<glyphInfo>
		<fontGlyph glyphRefID="71" glyphName="location" />
		<unicodeList>
			<unicode value="U+E101" charName="&lt;Private Use Character U+E101&gt;" />
		</unicodeList>
	</glyphInfo>
	<glyphInfo>
		<fontGlyph glyphRefID="72" glyphName="cal.day" />
		<unicodeList>
			<unicode value="U+E043" charName="&lt;Private Use Character U+E043&gt;" />
		</unicodeList>
	</glyphInfo>
	<glyphInfo>
		<fontGlyph glyphRefID="73" glyphName="cal.day.outline" />
		<unicodeList>
			<unicode value="U+E042" charName="&lt;Private Use Character U+E042&gt;" />
		</unicodeList>
	</glyphInfo>
	<glyphInfo>
		<fontGlyph glyphRefID="74" glyphName="cal.outline" />
		<unicodeList>
			<unicode value="U+E040" charName="&lt;Private Use Character U+E040&gt;" />
		</unicodeList>
	</glyphInfo>
	<glyphInfo>
		<fontGlyph glyphRefID="75" glyphName="location.arrow" />
		<unicodeList>
			<unicode value="U+E105" charName="&lt;Private Use Character U+E105&gt;" />
		</unicodeList>
	</glyphInfo>
	<glyphInfo>
		<fontGlyph glyphRefID="76" glyphName="location.arrow.outline" />
		<unicodeList>
			<unicode value="U+E104" charName="&lt;Private Use Character U+E104&gt;" />
		</unicodeList>
	</glyphInfo>
	<glyphInfo>
		<fontGlyph glyphRefID="77" glyphName="location.outline" />
		<unicodeList>
			<unicode value="U+E100" charName="&lt;Private Use Character U+E100&gt;" />
		</unicodeList>
	</glyphInfo>
	<glyphInfo>
		<fontGlyph glyphRefID="78" glyphName="map.marker" />
		<unicodeList>
			<unicode value="U+E103" charName="&lt;Private Use Character U+E103&gt;" />
		</unicodeList>
	</glyphInfo>
	<glyphInfo>
		<fontGlyph glyphRefID="79" glyphName="map.marker.outline" />
		<unicodeList>
			<unicode value="U+E102" charName="&lt;Private Use Character U+E102&gt;" />
		</unicodeList>
	</glyphInfo>
	<namedGlyphGroup isAltForms="yes">
		<fontGlyph glyphRefID="24" glyphName="square" />
		<fontGlyph glyphRefID="25" glyphName="square.check" />
		<fontGlyph glyphRefID="26" glyphName="square.plus" />
		<fontGlyph glyphRefID="27" glyphName="square.minus" />
		<fontGlyph glyphRefID="28" glyphName="square.x" />
		<fontGlyph glyphRefID="29" glyphName="square.outline" />
		<fontGlyph glyphRefID="30" glyphName="square.check.outline" />
		<fontGlyph glyphRefID="31" glyphName="square.plus.outline" />
		<fontGlyph glyphRefID="32" glyphName="square.minusoutline" />
		<fontGlyph glyphRefID="33" glyphName="square.x.outline" />
		<fontGlyph glyphRefID="34" glyphName="square.dash" />
		<fontGlyph glyphRefID="35" glyphName="square.check.dash" />
		<fontGlyph glyphRefID="36" glyphName="square.plus.dash" />
		<fontGlyph glyphRefID="37" glyphName="square.minus.dash" />
		<fontGlyph glyphRefID="38" glyphName="square.x.dash" />
	</namedGlyphGroup>
	<namedGlyphGroup isAltForms="yes">
		<fontGlyph glyphRefID="52" glyphName="circle" />
		<fontGlyph glyphRefID="16" glyphName="circle.triangle.up.outline" />
		<fontGlyph glyphRefID="17" glyphName="circle.triangle.down.outline" />
		<fontGlyph glyphRefID="18" glyphName="circle.triangle.left.outline" />
		<fontGlyph glyphRefID="19" glyphName="circle.triangle.right.outline" />
		<fontGlyph glyphRefID="20" glyphName="circle.triangle.up" />
		<fontGlyph glyphRefID="21" glyphName="circle.triangle.down" />
		<fontGlyph glyphRefID="22" glyphName="circle.triangle.left" />
		<fontGlyph glyphRefID="23" glyphName="circle.triangle.right" />
		<fontGlyph glyphRefID="39" glyphName="circle.outline" />
		<fontGlyph glyphRefID="40" glyphName="circle.check.outline" />
		<fontGlyph glyphRefID="41" glyphName="circle.plus.outline" />
		<fontGlyph glyphRefID="42" glyphName="circle.minus.outline" />
		<fontGlyph glyphRefID="43" glyphName="circle.x.outline" />
		<fontGlyph glyphRefID="44" glyphName="circle.chevron.up" />
		<fontGlyph glyphRefID="45" glyphName="circle.chevron.down" />
		<fontGlyph glyphRefID="46" glyphName="circle.chevron.left" />
		<fontGlyph glyphRefID="47" glyphName="circle.chevron.right" />
		<fontGlyph glyphRefID="48" glyphName="circle.chevron.up.outline" />
		<fontGlyph glyphRefID="49" glyphName="circle.chevron.right.outline" />
		<fontGlyph glyphRefID="50" glyphName="circle.chevron.down.outline" />
		<fontGlyph glyphRefID="51" glyphName="circle.chevron.left.outline" />
		<fontGlyph glyphRefID="53" glyphName="circle.check" />
		<fontGlyph glyphRefID="54" glyphName="circle.plus" />
		<fontGlyph glyphRefID="55" glyphName="circle.minus" />
		<fontGlyph glyphRefID="56" glyphName="circle.x" />
	</namedGlyphGroup>
	<namedGlyphGroup isAltForms="yes">
		<fontGlyph glyphRefID="57" glyphName="clock" />
		<fontGlyph glyphRefID="58" glyphName="clock.invert" />
		<fontGlyph glyphRefID="59" glyphName="clock.reverse" />
	</namedGlyphGroup>
	<namedGlyphGroup isAltForms="yes">
		<fontGlyph glyphRefID="60" glyphName="uni23F1" />
		<fontGlyph glyphRefID="61" glyphName="uni23F1.invert" />
	</namedGlyphGroup>
	<namedGlyphGroup isAltForms="yes">
		<fontGlyph glyphRefID="65" glyphName="comment" />
		<fontGlyph glyphRefID="64" glyphName="comment.outline" />
	</namedGlyphGroup>
	<namedGlyphGroup isAltForms="yes">
		<fontGlyph glyphRefID="66" glyphName="reply" />
		<fontGlyph glyphRefID="67" glyphName="reply.outline" />
	</namedGlyphGroup>
	<namedGlyphGroup isAltForms="yes">
		<fontGlyph glyphRefID="70" glyphName="cal" />
		<fontGlyph glyphRefID="72" glyphName="cal.day" />
		<fontGlyph glyphRefID="73" glyphName="cal.day.outline" />
		<fontGlyph glyphRefID="74" glyphName="cal.outline" />
	</namedGlyphGroup>
	<namedGlyphGroup isAltForms="yes">
		<fontGlyph glyphRefID="71" glyphName="location" />
		<fontGlyph glyphRefID="75" glyphName="location.arrow" />
		<fontGlyph glyphRefID="76" glyphName="location.arrow.outline" />
		<fontGlyph glyphRefID="77" glyphName="location.outline" />
	</namedGlyphGroup>
</ZapfTable>

